torchnlp/__init__.py
torchnlp/download.py
torchnlp/random.py
torchnlp/utils.py
torchnlp/_third_party/__init__.py
torchnlp/_third_party/lazy_loader.py
torchnlp/_third_party/weighted_random_sampler.py
torchnlp/datasets/__init__.py
torchnlp/datasets/count.py
torchnlp/datasets/dataset.py
torchnlp/datasets/imdb.py
torchnlp/datasets/iwslt.py
torchnlp/datasets/multi30k.py
torchnlp/datasets/penn_treebank.py
torchnlp/datasets/reverse.py
torchnlp/datasets/simple_qa.py
torchnlp/datasets/smt.py
torchnlp/datasets/snli.py
torchnlp/datasets/trec.py
torchnlp/datasets/ud_pos.py
torchnlp/datasets/wikitext_2.py
torchnlp/datasets/wmt.py
torchnlp/datasets/zero.py
torchnlp/encoders/__init__.py
torchnlp/encoders/encoder.py
torchnlp/encoders/label_encoder.py
torchnlp/encoders/text/__init__.py
torchnlp/encoders/text/character_encoder.py
torchnlp/encoders/text/default_reserved_tokens.py
torchnlp/encoders/text/delimiter_encoder.py
torchnlp/encoders/text/moses_encoder.py
torchnlp/encoders/text/spacy_encoder.py
torchnlp/encoders/text/static_tokenizer_encoder.py
torchnlp/encoders/text/subword_encoder.py
torchnlp/encoders/text/subword_text_tokenizer.py
torchnlp/encoders/text/text_encoder.py
torchnlp/encoders/text/treebank_encoder.py
torchnlp/encoders/text/whitespace_encoder.py
torchnlp/metrics/__init__.py
torchnlp/metrics/accuracy.py
torchnlp/metrics/bleu.py
torchnlp/nn/__init__.py
torchnlp/nn/attention.py
torchnlp/nn/cnn_encoder.py
torchnlp/nn/lock_dropout.py
torchnlp/nn/weight_drop.py
torchnlp/samplers/__init__.py
torchnlp/samplers/balanced_sampler.py
torchnlp/samplers/bptt_batch_sampler.py
torchnlp/samplers/bptt_sampler.py
torchnlp/samplers/bucket_batch_sampler.py
torchnlp/samplers/deterministic_sampler.py
torchnlp/samplers/distributed_batch_sampler.py
torchnlp/samplers/distributed_sampler.py
torchnlp/samplers/noisy_sorted_batch_sampler.py
torchnlp/samplers/noisy_sorted_sampler.py
torchnlp/samplers/oom_batch_sampler.py
torchnlp/samplers/repeat_sampler.py
pytorch_nlp-0.5.0.dist-info/LICENSE
pytorch_nlp-0.5.0.dist-info/METADATA
pytorch_nlp-0.5.0.dist-info/WHEEL
pytorch_nlp-0.5.0.dist-info/top_level.txt
pytorch_nlp-0.5.0.dist-info/zip-safe
pytorch_nlp-0.5.0.dist-info/RECORD
